shmx-1.0.1.dist-info/RECORD
shmx-1.0.1.dist-info/WHEEL
shmx-1.0.1.dist-info/top_level.txt
shmx-1.0.1.dist-info/METADATA
shmx/__init__.pyi
shmx/__init__.py
shmx/shmx_core.cpython-313-darwin.so
shmx/py.typed
